libfelix/__init__.py
libfelix/filesystem.py
libfelix/git.py
libfelix/logging.py
libfelix/md.py
libfelix/regex.py
libfelix/rename_scans.py
libfelix/music/__init__.py
libfelix/music/api.py
libfelix/music/cli.py
libfelix-0.7.1.dist-info/licenses/LICENSE
libfelix-0.7.1.dist-info/METADATA
libfelix-0.7.1.dist-info/WHEEL
libfelix-0.7.1.dist-info/entry_points.txt
libfelix-0.7.1.dist-info/top_level.txt
libfelix-0.7.1.dist-info/RECORD
