Metadata-Version: 2.4
Name: libfelix
Version: 0.7.1
Summary: Felix' library
Author-email: Felix Hummel <felix@felixhummel.de>
Project-URL: Repository, https://gitlab.com/felixhummel/libfelix/
Requires-Python: >=3.11
License-File: LICENSE
Requires-Dist: structlog>=25.1.0
Provides-Extra: music
Requires-Dist: dbus-python>=1.4.0; extra == "music"
Provides-Extra: cli
Requires-Dist: click>=8.2.1; extra == "cli"
Provides-Extra: rename-scans
Requires-Dist: python-dateutil>=2.9.0.post0; extra == "rename-scans"
Requires-Dist: inotify>=0.2.12; extra == "rename-scans"
Dynamic: license-file
